tests/__init__.py
tests/grids/__init__.py
tests/grids/test_grid_jax.py
tests/grids/test_grid_warp.py
tests/kernels/__init__.py
xlb/__init__.py
xlb/compute_backend.py
xlb/default_config.py
xlb/grid_backend.py
xlb/physics_type.py
xlb/precision_policy.py
xlb/distribute/__init__.py
xlb/distribute/distribute.py
xlb/experimental/__init__.py
xlb/experimental/ooc/__init__.py
xlb/experimental/ooc/ooc_array.py
xlb/experimental/ooc/out_of_core.py
xlb/experimental/ooc/utils.py
xlb/experimental/ooc/tiles/__init__.py
xlb/experimental/ooc/tiles/compressed_tile.py
xlb/experimental/ooc/tiles/dense_tile.py
xlb/experimental/ooc/tiles/dynamic_array.py
xlb/experimental/ooc/tiles/tile.py
xlb/grid/__init__.py
xlb/grid/grid.py
xlb/grid/jax_grid.py
xlb/grid/warp_grid.py
xlb/helper/__init__.py
xlb/helper/check_boundary_overlaps.py
xlb/helper/initializers.py
xlb/helper/nse_solver.py
xlb/operator/__init__.py
xlb/operator/operator.py
xlb/operator/parallel_operator.py
xlb/operator/boundary_condition/__init__.py
xlb/operator/boundary_condition/bc_do_nothing.py
xlb/operator/boundary_condition/bc_equilibrium.py
xlb/operator/boundary_condition/bc_extrapolation_outflow.py
xlb/operator/boundary_condition/bc_fullway_bounce_back.py
xlb/operator/boundary_condition/bc_grads_approximation.py
xlb/operator/boundary_condition/bc_halfway_bounce_back.py
xlb/operator/boundary_condition/bc_regularized.py
xlb/operator/boundary_condition/bc_zouhe.py
xlb/operator/boundary_condition/boundary_condition.py
xlb/operator/boundary_condition/boundary_condition_registry.py
xlb/operator/boundary_masker/__init__.py
xlb/operator/boundary_masker/indices_boundary_masker.py
xlb/operator/boundary_masker/mesh_boundary_masker.py
xlb/operator/boundary_masker/mesh_distance_boundary_masker.py
xlb/operator/collision/__init__.py
xlb/operator/collision/bgk.py
xlb/operator/collision/collision.py
xlb/operator/collision/forced_collision.py
xlb/operator/collision/kbc.py
xlb/operator/equilibrium/__init__.py
xlb-0.2.1.dist-info/AUTHORS
xlb-0.2.1.dist-info/LICENSE
xlb-0.2.1.dist-info/METADATA
xlb-0.2.1.dist-info/WHEEL
xlb-0.2.1.dist-info/dependency_links.txt
xlb-0.2.1.dist-info/top_level.txt
xlb-0.2.1.dist-info/RECORD
