Metadata-Version: 2.1
Name: xlb
Version: 0.2.1
Summary: XLB: Accelerated Lattice Boltzmann (XLB) for Physics-based ML
Home-page: https://github.com/Autodesk/XLB
Author: Mehdi Ataei
License: Apache License 2.0
Requires-Python: >=3.10
License-File: LICENSE
License-File: AUTHORS
Requires-Dist: matplotlib>=3.9.2
Requires-Dist: numpy>=2.1.2
Requires-Dist: pyvista>=0.44.1
Requires-Dist: trimesh>=4.4.9
Requires-Dist: warp-lang>=1.4.0
Requires-Dist: numpy-stl>=3.1.2
Requires-Dist: pydantic>=2.9.1
Requires-Dist: ruff>=0.6.5
Requires-Dist: jax>=0.4.34
Provides-Extra: cuda
Requires-Dist: jax[cuda12]>=0.4.34; extra == "cuda"
Provides-Extra: tpu
Requires-Dist: jax[tpu]>=0.4.34; extra == "tpu"
